langrila/__init__.py
langrila/anthropic/__init__.py
langrila/anthropic/client.py
langrila/aws/__init__.py
langrila/aws/client.py
langrila/core/__init__.py
langrila/core/_context.py
langrila/core/agent.py
langrila/core/client.py
langrila/core/config.py
langrila/core/embedding.py
langrila/core/error.py
langrila/core/griffe.py
langrila/core/internal_prompt.py
langrila/core/logger.py
langrila/core/memory.py
langrila/core/message.py
langrila/core/metadata.py
langrila/core/model.py
langrila/core/prompt.py
langrila/core/pydantic.py
langrila/core/pydantic_utils.py
langrila/core/response.py
langrila/core/retrieval.py
langrila/core/tool.py
langrila/core/typing.py
langrila/core/usage.py
langrila/database/__init__.py
langrila/database/base.py
langrila/database/chroma.py
langrila/database/metadata_store/sqlite.py
langrila/database/qdrant.py
langrila/database/usearch.py
langrila/file_utils/pdf.py
langrila/file_utils/video.py
langrila/filter/.gitkeep
langrila/filter/metadata/__init__.py
langrila/filter/metadata/base.py
langrila/filter/metadata/sqlite.py
langrila/google/__init__.py
langrila/google/client.py
langrila/google/gemini_utils.py
langrila/memory/cosmos.py
langrila/memory/in_memory.py
langrila/memory/json.py
langrila/memory/pickle.py
langrila/memory/s3.py
langrila/openai/__init__.py
langrila/openai/client.py
langrila/prompt_template.py
langrila/sample.py
langrila/utils.py
langrila/warnings.py
langrila-1.2.4.dist-info/LICENSE
langrila-1.2.4.dist-info/METADATA
langrila-1.2.4.dist-info/WHEEL
langrila-1.2.4.dist-info/RECORD
