Metadata-Version: 2.1
Name: langrila
Version: 1.2.4
Summary: Useful tool to build multi-agent in an easy way
Home-page: https://github.com/taikinman/langrila
Author: taikinman
Author-email: okipedia6161@gmail.com
Requires-Python: >=3.10,<3.13
Classifier: Programming Language :: Python :: 3
Classifier: Programming Language :: Python :: 3.10
Classifier: Programming Language :: Python :: 3.11
Classifier: Programming Language :: Python :: 3.12
Provides-Extra: all
Provides-Extra: audio
Provides-Extra: bedrock
Provides-Extra: chroma
Provides-Extra: claude
Provides-Extra: cosmos
Provides-Extra: gemini
Provides-Extra: openai
Provides-Extra: pdf
Provides-Extra: qdrant
Provides-Extra: s3
Provides-Extra: usearch
Provides-Extra: video
Requires-Dist: anthropic (>=0.40.0,<0.41.0) ; extra == "claude" or extra == "all"
Requires-Dist: azure-cosmos (>=4.7.0,<5.0.0) ; extra == "cosmos" or extra == "all"
Requires-Dist: boto3 (>=1.35.0,<2.0.0) ; extra == "s3" or extra == "bedrock" or extra == "all"
Requires-Dist: chromadb (>=0.5.0,<0.6.0) ; extra == "chroma" or extra == "all"
Requires-Dist: google-genai (>=0.3.0,<0.4.0) ; extra == "gemini" or extra == "all"
Requires-Dist: griffe (>=1.5.1,<2.0.0)
Requires-Dist: imageio (>=2.34.2,<3.0.0) ; extra == "video" or extra == "all"
Requires-Dist: imageio-ffmpeg (>=0.5.1,<0.6.0) ; extra == "video" or extra == "all"
Requires-Dist: loguru (>=0.7.3,<0.8.0)
Requires-Dist: matplotlib (>=3.8.0,<4.0.0)
Requires-Dist: moviepy (>=1.0.3,<2.0.0) ; extra == "audio" or extra == "all"
Requires-Dist: numpy (>=1.26.1,<2.0.0)
Requires-Dist: openai (>=1.57.4,<2.0.0) ; extra == "openai" or extra == "all"
Requires-Dist: pandas (>=2.1.1,<3.0.0)
Requires-Dist: plotly (>=5.17.0,<6.0.0)
Requires-Dist: pydantic (>=2.10.0,<3.0.0)
Requires-Dist: pypdfium2 (>=4.30.0,<5.0.0) ; extra == "pdf" or extra == "all"
Requires-Dist: qdrant-client (>=1.9.1,<2.0.0) ; extra == "qdrant" or extra == "all"
Requires-Dist: scikit-learn (>=1.3.2,<2.0.0)
Requires-Dist: scipy (>=1.11.3,<2.0.0)
Requires-Dist: soundfile (>=0.12.1,<0.13.0) ; extra == "audio" or extra == "all"
Requires-Dist: tiktoken (>=0.8.0,<0.9.0) ; extra == "openai" or extra == "all"
Requires-Dist: usearch (>=2.16.9,<3.0.0) ; extra == "usearch" or extra == "all"
Project-URL: Repository, https://github.com/taikinman/langrila
